README.md
setup.cfg
setup.py
ktk_distributions/Binomialdistribution.py
ktk_distributions/Gaussiandistribution.py
ktk_distributions/Generaldistribution.py
ktk_distributions/__init__.py
ktk_distributions.egg-info/PKG-INFO
ktk_distributions.egg-info/SOURCES.txt
ktk_distributions.egg-info/dependency_links.txt
ktk_distributions.egg-info/not-zip-safe
ktk_distributions.egg-info/top_level.txt