Metadata-Version: 1.0
Name: ktk-distributions
Version: 0.1
Summary: Gaussian distributions,Binomial distributions
Home-page: UNKNOWN
Author: Kartikey Singh
Author-email: UNKNOWN
License: UNKNOWN
Platform: UNKNOWN
